mofa/__init__.py
mofa/core/BayesNet.py
mofa/core/__init__.py
mofa/core/build_model.py
mofa/core/distributions.py
mofa/core/entry_point.py
mofa/core/init_asd.py
mofa/core/init_asd2.py
mofa/core/init_nodes.py
mofa/core/mixed_nodes.py
mofa/core/multiview_nodes.py
mofa/core/nodes.py
mofa/core/nongaussian_nodes.py
mofa/core/simulate.py
mofa/core/updates.py
mofa/core/utils.py
mofa/core/variational_nodes.py
mofa/core/warp/__init__.py
mofa/core/warp/factor_functions.py
mofa/core/warp/warping_functions.py
mofa/core/warp/warping_inference.py
mofa/run/__init__.py
mofa/run/python_template.py
mofapy/__init__.py
mofapy/core/BayesNet.py
mofapy/core/__init__.py
mofapy/core/build_model.py
mofapy/core/distributions.py
mofapy/core/entry_point.py
mofapy/core/init_nodes.py
mofapy/core/mixed_nodes.py
mofapy/core/multiview_nodes.py
mofapy/core/nodes.py
mofapy/core/nongaussian_nodes.py
mofapy/core/simulate.py
mofapy/core/updates.py
mofapy/core/utils.py
mofapy/core/variational_nodes.py
mofapy/run/__init__.py
mofapy/run/python_template.py
mofapy-1.0.dist-info/METADATA
mofapy-1.0.dist-info/RECORD
mofapy-1.0.dist-info/WHEEL
mofapy-1.0.dist-info/top_level.txt
