Metadata-Version: 2.1
Name: mofapy
Version: 1.0
Summary: Multi-Omics Factor Analysis
Home-page: https://github.com/PMBio/MOFA
Author: Ricard Argelaguet, Damien Arnol and Britta Velten
Author-email: ricard.argelaguet@gmail.com
License: MIT
Platform: UNKNOWN
Requires-Dist: pandas
Requires-Dist: scipy
Requires-Dist: numpy
Requires-Dist: sklearn
Requires-Dist: argparse
Requires-Dist: h5py
